{
  "type": "minecraft:blasting",
  "ingredient": [
    {
      "item": "qforgemod:tin_pickaxe"
    },
    {
      "item": "qforgemod:tin_shovel"
    },
    {
      "item": "qforgemod:tin_axe"
    },
    {
      "item": "qforgemod:tin_hoe"
    },
    {
      "item": "qforgemod:tin_sword"
    },
    {
      "item": "qforgemod:tin_helmet"
    },
    {
      "item": "qforgemod:tin_chestplate"
    },
    {
      "item": "qforgemod:tin_leggings"
    },
    {
      "item": "qforgemod:tin_boots"
    }
  ],
  "result": "qforgemod:tin_nugget",
  "experience": 0.1,
  "cookingtime": 100
}