{
  "type": "minecraft:smelting",
  "ingredient": [
    {
      "item": "randomthingz:ultrinium_pickaxe"
    },
    {
      "item": "randomthingz:ultrinium_shovel"
    },
    {
      "item": "randomthingz:ultrinium_axe"
    },
    {
      "item": "randomthingz:ultrinium_hoe"
    },
    {
      "item": "randomthingz:ultrinium_sword"
    },
    {
      "item": "randomthingz:ultrinium_helmet"
    },
    {
      "item": "randomthingz:ultrinium_chestplate"
    },
    {
      "item": "randomthingz:ultrinium_leggings"
    },
    {
      "item": "randomthingz:ultrinium_boots"
    }
  ],
  "result": "randomthingz:ultrinium_nugget",
  "experience": 7,
  "cookingtime": 900
}